LICENSE
MANIFEST.in
README.md
requirements.txt
setup.py
nbdt/__init__.py
nbdt/analysis.py
nbdt/graph.py
nbdt/hierarchy.py
nbdt/loss.py
nbdt/model.py
nbdt/utils.py
nbdt.egg-info/PKG-INFO
nbdt.egg-info/SOURCES.txt
nbdt.egg-info/dependency_links.txt
nbdt.egg-info/requires.txt
nbdt.egg-info/top_level.txt
nbdt/bin/nbdt
nbdt/bin/nbdt-hierarchy
nbdt/bin/nbdt-wnids
nbdt/data/__init__.py
nbdt/data/custom.py
nbdt/data/imagenet.py
nbdt/hierarchies/CIFAR10/graph-induced-ResNet10.json
nbdt/hierarchies/CIFAR10/graph-induced-ResNet18.json
nbdt/hierarchies/CIFAR10/graph-induced-wrn28_10_cifar10.json
nbdt/hierarchies/CIFAR10/graph-induced.json
nbdt/hierarchies/CIFAR10/graph-wordnet.json
nbdt/hierarchies/CIFAR100/graph-induced-ResNet18.json
nbdt/hierarchies/CIFAR100/graph-induced-wrn28_10_cifar100.json
nbdt/hierarchies/CIFAR100/graph-induced.json
nbdt/hierarchies/CIFAR100/graph-wordnet-single.json
nbdt/hierarchies/CIFAR100/graph-wordnet.json
nbdt/hierarchies/Imagenet1000/graph-induced-efficientnet_b7b.json
nbdt/hierarchies/TinyImagenet200/graph-induced-ResNet18.json
nbdt/hierarchies/TinyImagenet200/graph-induced-wrn28_10.json
nbdt/hierarchies/TinyImagenet200/graph-induced.json
nbdt/hierarchies/TinyImagenet200/graph-wordnet-single.json
nbdt/hierarchies/TinyImagenet200/graph-wordnet.json
nbdt/models/__init__.py
nbdt/models/resnet.py
nbdt/models/utils.py
nbdt/models/wideresnet.py
nbdt/templates/tree-template.html
nbdt/wnids/CIFAR10.txt
nbdt/wnids/CIFAR100.txt
nbdt/wnids/Imagenet1000.txt
nbdt/wnids/TinyImagenet200.txt