Metadata-Version: 2.1
Name: nbdt
Version: 0.0.4
Summary: Making decision trees competitive with state-of-the-art neural networks on CIFAR10, CIFAR100, TinyImagenet200, Imagenet. Transform any image classification neural network into an interpretable neural-backed decision tree.
Home-page: https://github.com/alvinwan/neural-backed-decision-trees
Author: Alvin Wan
Author-email: hi@alvinwan.com
License: UNKNOWN
Download-URL: https://github.com/alvinwan/neural-backed-decision-trees/archive/0.0.4.zip
Platform: UNKNOWN
Classifier: Intended Audience :: Developers
Classifier: Programming Language :: Python :: 3
Classifier: License :: OSI Approved :: MIT License
Classifier: Operating System :: OS Independent
Requires-Python: >=3.5
